compiler/__init__.py
compiler/compiler.py
compiler/languages.py
compiler-0.2.0.dist-info/DESCRIPTION.rst
compiler-0.2.0.dist-info/METADATA
compiler-0.2.0.dist-info/RECORD
compiler-0.2.0.dist-info/WHEEL
compiler-0.2.0.dist-info/metadata.json
compiler-0.2.0.dist-info/top_level.txt
