Metadata-Version: 1.2
Name: compiler
Version: 0.2.0
Summary: A data integrity check library
Home-page: https://github.com/xiaojieluo/vlde
Author: Luo Xiaojie
Author-email: xiaojieluoff@gmail.com
License: MIT License
